MANIFEST.in
setup.cfg
setup.py
tests/__init__.py
tests/test_access_token.py
tests/test_accounts.py
tests/test_addresses.py
tests/test_applications.py
tests/test_authorized_connect_apps.py
tests/test_available_phonenumber.py
tests/test_base_resource.py
tests/test_call_feedback.py
tests/test_calls.py
tests/test_client.py
tests/test_conferences.py
tests/test_connect_apps.py
tests/test_core.py
tests/test_credentials.py
tests/test_jwt.py
tests/test_keys.py
tests/test_make_request.py
tests/test_media.py
tests/test_members.py
tests/test_messages.py
tests/test_notifications.py
tests/test_phone_numbers.py
tests/test_queues.py
tests/test_recordings.py
tests/test_sms_messages.py
tests/test_tokens.py
tests/test_transcriptions.py
tests/test_twiml.py
tests/test_unicode.py
tests/test_usage.py
tests/test_validation.py
tests/tools.py
tests/ip_messaging/__init__.py
tests/ip_messaging/test_channels.py
tests/ip_messaging/test_credentials.py
tests/ip_messaging/test_members.py
tests/ip_messaging/test_messages.py
tests/ip_messaging/test_roles.py
tests/ip_messaging/test_services.py
tests/ip_messaging/test_users.py
tests/lookups/__init__.py
tests/lookups/test_client.py
tests/lookups/test_phone_numbers.py
tests/monitor/__init__.py
tests/monitor/test_alerts.py
tests/monitor/test_client.py
tests/monitor/test_events.py
tests/pricing/__init__.py
tests/pricing/test_messaging_countries.py
tests/pricing/test_numbers.py
tests/pricing/test_voice.py
tests/task_router/__init__.py
tests/task_router/test_activities.py
tests/task_router/test_capability.py
tests/task_router/test_events.py
tests/task_router/test_reservations.py
tests/task_router/test_statistics.py
tests/task_router/test_task_queues.py
tests/task_router/test_task_router_capability.py
tests/task_router/test_task_router_taskqueue_capability.py
tests/task_router/test_task_router_worker_capability.py
tests/task_router/test_task_router_workspace_capability.py
tests/task_router/test_tasks.py
tests/task_router/test_workers.py
twilio_fatisar.egg-info/PKG-INFO
twilio_fatisar.egg-info/SOURCES.txt
twilio_fatisar.egg-info/dependency_links.txt
twilio_fatisar.egg-info/requires.txt
twilio_fatisar.egg-info/top_level.txt